appsignal_beta/__init__.py
appsignal_beta-0.2.0.dist-info/METADATA
appsignal_beta-0.2.0.dist-info/WHEEL
appsignal_beta-0.2.0.dist-info/RECORD
